launch_on_workspace/__init__.py
launch_on_workspace/custom_launchers.py
launch_on_workspace/displays.py
launch_on_workspace/launcher.py
launch_on_workspace-1.1.1.dist-info/LICENSE
launch_on_workspace-1.1.1.dist-info/METADATA
launch_on_workspace-1.1.1.dist-info/WHEEL
launch_on_workspace-1.1.1.dist-info/top_level.txt
launch_on_workspace-1.1.1.dist-info/RECORD
