Metadata-Version: 2.1
Name: launch-on-workspace
Version: 1.1.1
Summary: Launch applications on a given workspace and given monitor in Linux
Home-page: https://github.com/xblahoud/launch_on_workspace
Author: Fanda Blahoudek
Author-email: fandikb+low@gmail.com
License: MIT
Platform: UNKNOWN
Classifier: License :: OSI Approved :: MIT License
Classifier: Programming Language :: Python :: 3
Classifier: Programming Language :: Python :: 3.6
Requires-Python: >=3.6.0
